{
  "base_url": "https://open.bigmodel.cn/api/paas/v4",
  "model": "autoglm-phone",
  "apikey": "ad6344498524401182c98c2658196208.JhJVvBBpQ5dUCKcs",
  "task": "1. 杀掉小红书的进程，返回桌面后打开小红书应用。 2. 进入“发现”页面并下拉刷新。 3. 浏览并选择一个帖子。 4. 进入该帖子的评论区。 5. 阅读帖子及评论内容。 6. 撰写并发布一条包含文字和表情的评论。 7. 返回“发现”页面。 8. 重复步骤3至7，共完成2次不同的评论。",
  "max_steps": 20000,
  "temperature": 0.2,
  "device_type": "adb",
  "selected_device": "",
  "remote_connection": {
    "ip": "192.168.1.100",
    "port": "5555"
  },
  "wireless_pair": {
    "pair_address": "10.10.10.100:41717",
    "connect_address": "10.10.10.100:5555"
  },
  "legacy_wireless": {
    "ip": "192.168.1.100",
    "port": "5555"
  },
  "ios_device_ip": "localhost"
}